ByteTrack/setup.py
ByteTrack/deploy/ONNXRuntime/onnx_inference.py
ByteTrack/exps/default/nano.py
ByteTrack/exps/default/yolov3.py
ByteTrack/exps/default/yolox_l.py
ByteTrack/exps/default/yolox_m.py
ByteTrack/exps/default/yolox_s.py
ByteTrack/exps/default/yolox_tiny.py
ByteTrack/exps/default/yolox_x.py
ByteTrack/exps/example/mot/yolox_l_mix_det.py
ByteTrack/exps/example/mot/yolox_m_mix_det.py
ByteTrack/exps/example/mot/yolox_nano_mix_det.py
ByteTrack/exps/example/mot/yolox_s_mix_det.py
ByteTrack/exps/example/mot/yolox_tiny_mix_det.py
ByteTrack/exps/example/mot/yolox_x_ablation.py
ByteTrack/exps/example/mot/yolox_x_ch.py
ByteTrack/exps/example/mot/yolox_x_mix_det.py
ByteTrack/exps/example/mot/yolox_x_mix_mot20_ch.py
ByteTrack/exps/example/mot/yolox_x_mot17_half.py
ByteTrack/src/cython-bbox/setup.py
ByteTrack/tools/convert_cityperson_to_coco.py
ByteTrack/tools/convert_crowdhuman_to_coco.py
ByteTrack/tools/convert_ethz_to_coco.py
ByteTrack/tools/convert_mot17_to_coco.py
ByteTrack/tools/convert_mot20_to_coco.py
ByteTrack/tools/convert_video.py
ByteTrack/tools/demo_track.py
ByteTrack/tools/export_onnx.py
ByteTrack/tools/interpolation.py
ByteTrack/tools/mix_data_ablation.py
ByteTrack/tools/mix_data_test_mot17.py
ByteTrack/tools/mix_data_test_mot20.py
ByteTrack/tools/mota.py
ByteTrack/tools/track.py
ByteTrack/tools/track_deepsort.py
ByteTrack/tools/track_motdt.py
ByteTrack/tools/track_sort.py
ByteTrack/tools/train.py
ByteTrack/tools/trt.py
ByteTrack/tools/txt2video.py
ByteTrack/tutorials/centertrack/byte_tracker.py
ByteTrack/tutorials/centertrack/opts.py
ByteTrack/tutorials/centertrack/tracker.py
ByteTrack/tutorials/centertrack/mot_online/basetrack.py
ByteTrack/tutorials/centertrack/mot_online/kalman_filter.py
ByteTrack/tutorials/centertrack/mot_online/matching.py
ByteTrack/tutorials/cstrack/byte_tracker.py
ByteTrack/tutorials/cstrack/tracker.py
ByteTrack/tutorials/ctracker/byte_tracker.py
ByteTrack/tutorials/ctracker/eval_motchallenge.py
vid2info-1.86.dist-info/LICENSE
vid2info-1.86.dist-info/METADATA
vid2info-1.86.dist-info/WHEEL
vid2info-1.86.dist-info/dependency_links.txt
vid2info-1.86.dist-info/top_level.txt
vid2info-1.86.dist-info/RECORD
