Metadata-Version: 2.1
Name: vid2info
Version: 1.86
Summary: Vid2Info is an easy-to-use Computer Vision pipeline that implements Detection, Tracking and, optionally, Segmentation.
Home-page: https://github.com/Eric-Canas/vid2info
Author: Eric Canas
Author-email: elcorreodeharu@gmail.com
License: MIT
Platform: UNKNOWN
Classifier: Development Status :: 3 - Alpha
Classifier: Intended Audience :: Developers
Classifier: Intended Audience :: Education
Classifier: Intended Audience :: Science/Research
Classifier: License :: OSI Approved :: MIT License
Classifier: Topic :: Scientific/Engineering :: Artificial Intelligence
Classifier: Topic :: Software Development
Classifier: Topic :: Software Development :: Libraries
Classifier: Programming Language :: Python :: 3
License-File: LICENSE
Requires-Dist: numpy
Requires-Dist: matplotlib
Requires-Dist: pycocotools
Requires-Dist: scipy
Requires-Dist: cython
Requires-Dist: opencv-python
